title2bib/__init__.py
title2bib/crossref.py
title2bib/bin/title2bib
title2bib-0.4.1.data/scripts/title2bib
title2bib-0.4.1.dist-info/LICENSE
title2bib-0.4.1.dist-info/METADATA
title2bib-0.4.1.dist-info/WHEEL
title2bib-0.4.1.dist-info/top_level.txt
title2bib-0.4.1.dist-info/RECORD
