Metadata-Version: 2.1
Name: title2bib
Version: 0.4.1
Summary: Given a title  returns a bibtex
Home-page: https://github.com/bibcure/title2bib
Author: Bruno Messias
Author-email: messias.physics@gmail.com
License: MIT
Download-URL: https://github.com/bibcure/title2bib/archive/0.4.1.tar.gz
Keywords: bibtex,science,scientific-journals,crosref
Platform: UNKNOWN
Classifier: License :: OSI Approved :: MIT License
Classifier: Intended Audience :: Science/Research
Classifier: Programming Language :: Python
Classifier: Topic :: Text Processing :: Markup :: LaTeX
Requires-Dist: requests
Requires-Dist: future
Requires-Dist: doi2bib
Requires-Dist: arxivcheck
Requires-Dist: unidecode
